pyauxlib/__init__.py
pyauxlib/callables/__init__.py
pyauxlib/callables/args.py
pyauxlib/callables/callables.py
pyauxlib/decorators/__init__.py
pyauxlib/decorators/import_errors.py
pyauxlib/decorators/log.py
pyauxlib/decorators/timer.py
pyauxlib/decorators/warning.py
pyauxlib/experimental/__init__.py
pyauxlib/experimental/bom.py
pyauxlib/experimental/get_caller_path.py
pyauxlib/experimental/kwargs.py
pyauxlib/experimental/lists.py
pyauxlib/fileutils/__init__.py
pyauxlib/fileutils/compressed.py
pyauxlib/fileutils/filegroup.py
pyauxlib/fileutils/filesfolders.py
pyauxlib/fileutils/find.py
pyauxlib/fileutils/utils.py
pyauxlib/fileutils/yamlio.py
pyauxlib/py.typed
pyauxlib/utils/__init__.py
pyauxlib/utils/dates.py
pyauxlib/utils/dictionaries.py
pyauxlib/utils/encoding.py
pyauxlib/utils/inspect_callables.py
pyauxlib/utils/logger.py
pyauxlib/utils/memory.py
pyauxlib/utils/netcdf.py
pyauxlib/utils/timer.py
pyauxlib/utils/uuid_manager.py
pyauxlib/utils/zip.py
pyauxlib-0.14.1.dist-info/licenses/LICENSE
pyauxlib-0.14.1.dist-info/WHEEL
pyauxlib-0.14.1.dist-info/METADATA
pyauxlib-0.14.1.dist-info/RECORD
