Metadata-Version: 2.4
Name: pyauxlib
Version: 0.14.1
Summary: Auxiliary library for python.
Keywords: pyauxlib
Author: Pablo Solís-Fernández
Author-email: Pablo Solís-Fernández <psolsfer@gmail.com>
License-Expression: BSD-3-Clause
License-File: LICENSE
Classifier: Development Status :: 2 - Pre-Alpha
Classifier: Intended Audience :: Developers
Classifier: Intended Audience :: Science/Research
Classifier: License :: OSI Approved :: BSD License
Classifier: Natural Language :: English
Classifier: Programming Language :: Python :: 3
Classifier: Programming Language :: Python :: 3.10
Classifier: Programming Language :: Python :: 3.11
Classifier: Programming Language :: Python :: 3.12
Classifier: Programming Language :: Python :: 3.13
Classifier: Programming Language :: Python :: 3.14
Classifier: Topic :: Scientific/Engineering
Classifier: Typing :: Typed
Requires-Dist: pydantic>=2.4.0
Requires-Dist: ruamel-yaml<1.0
Requires-Dist: wrapt>=1.15
Requires-Dist: chardet<6.0 ; extra == 'all'
Requires-Dist: python-dateutil ; extra == 'all'
Requires-Dist: types-python-dateutil ; extra == 'all'
Requires-Dist: tzlocal ; extra == 'all'
Requires-Dist: chardet<6.0 ; extra == 'chardet'
Requires-Dist: python-dateutil ; extra == 'dates'
Requires-Dist: types-python-dateutil ; extra == 'dates'
Requires-Dist: tzlocal ; extra == 'times'
Maintainer: Pablo Solís-Fernández
Maintainer-email: Pablo Solís-Fernández <psolsfer@gmail.com>
Requires-Python: >=3.10, <3.15
Project-URL: Documentation, https://pyauxlib.readthedocs.io
Project-URL: Homepage, https://github.com/psolsfer/pyauxlib
Project-URL: Issues, https://github.com/psolsfer/pyauxlib/issues
Project-URL: Repository, https://github.com/psolsfer/pyauxlib
Provides-Extra: all
Provides-Extra: chardet
Provides-Extra: dates
Provides-Extra: times
